SatiyaMingxiang/README.md
SatiyaMingxiang/__init__.py
SatiyaMingxiang/__main__.py
SatiyaMingxiang/file.pdf
SatiyaMingxiang/index.html
satiya_mingxiang-2022.12.8.0.dist-info/METADATA
satiya_mingxiang-2022.12.8.0.dist-info/WHEEL
satiya_mingxiang-2022.12.8.0.dist-info/entry_points.txt
satiya_mingxiang-2022.12.8.0.dist-info/top_level.txt
satiya_mingxiang-2022.12.8.0.dist-info/RECORD
